fb2epubru_dl.py
fb2epubru_dl-0.1.dev5.dist-info/LICENSE
fb2epubru_dl-0.1.dev5.dist-info/METADATA
fb2epubru_dl-0.1.dev5.dist-info/WHEEL
fb2epubru_dl-0.1.dev5.dist-info/entry_points.txt
fb2epubru_dl-0.1.dev5.dist-info/top_level.txt
fb2epubru_dl-0.1.dev5.dist-info/RECORD
